sfalmanac/__init__.py
sfalmanac/__main__.py
sfalmanac/astro-data/__init__.py
sfalmanac/astro-data/de421.bsp
sfalmanac/astro-data/hip_main.dat
sfalmanac/data/A4chart0-180_P.pdf
sfalmanac/data/A4chart180-360_P.pdf
sfalmanac/data/Ra.jpg
sfalmanac/data/__init__.py
sfalmanac/data/croppedmoon.png
sfalmanac/docs/Explanation.pdf
sfalmanac/docs/__init__.py
sfalmanac/lib/__init__.py
sfalmanac/lib/alma_skyfield.py
sfalmanac/lib/config.py
sfalmanac/lib/eventtables.py
sfalmanac/lib/increments.py
sfalmanac/lib/ld_charts.py
sfalmanac/lib/ld_skyfield.py
sfalmanac/lib/ld_stardata.py
sfalmanac/lib/ld_tables.py
sfalmanac/lib/mp_eventtables.py
sfalmanac/lib/mp_nautical.py
sfalmanac/lib/nautical.py
sfalmanac/lib/suntables.py
sfalmanac-1.12.5.dist-info/LICENSE
sfalmanac-1.12.5.dist-info/METADATA
sfalmanac-1.12.5.dist-info/WHEEL
sfalmanac-1.12.5.dist-info/top_level.txt
sfalmanac-1.12.5.dist-info/RECORD
